setup.py
src/impaf_alembic.egg-info/PKG-INFO
src/impaf_alembic.egg-info/SOURCES.txt
src/impaf_alembic.egg-info/dependency_links.txt
src/impaf_alembic.egg-info/namespace_packages.txt
src/impaf_alembic.egg-info/not-zip-safe
src/impaf_alembic.egg-info/requires.txt
src/impaf_alembic.egg-info/top_level.txt
src/implugin/__init__.py
src/implugin/alembic/__init__.py
src/implugin/alembic/commands.py
src/implugin/alembic/test_commands.py